Metadata-Version: 1.0
Name: magicdice
Version: 0.0.1
Summary: A Python library to interact with the magic-dice game
Home-page: https://github.com/emre/magicdice
Author: Emre Yilmaz
Author-email: mail@emreyilmaz.me
License: MIT
Platform: UNKNOWN
